{"generated": "2026-07-23 10:53 UTC", "books": ["dabble", "ladbrokes", "pointsbet", "sportsbet", "tab"], "count": 10, "matches": [{"tour": "atp", "date": "", "tournament": "Zug Open", "round": "Round 2", "surface": "Hard", "player1": "Marc Andrea Huesler", "player2": "Juan Bautista Torres", "thin": true, "markets": [{"key": "mw", "label": "Match winner", "selections": [{"id": "mw|1", "label": "Marc Andrea Huesler", "model": 0.3914, "fair": 2.55, "books": {"sportsbet": 1.4, "ladbrokes": 1.4, "tab": 1.38, "dabble": 1.4}, "best": {"price": 1.4, "book": "sportsbet"}, "ev": -0.452, "edge": -0.3229}, {"id": "mw|2", "label": "Juan Bautista Torres", "model": 0.6086, "fair": 1.64, "books": {"sportsbet": 2.7, "ladbrokes": 2.8, "tab": 2.8, "dabble": 2.8}, "best": {"price": 2.8, "book": "ladbrokes"}, "ev": 0.7041, "edge": 0.2515}]}, {"key": "sb", "label": "Set betting", "selections": [{"id": "sb|0-2", "label": "Juan Bautista Torres 2-0", "model": 0.2848, "fair": 3.51, "books": {"sportsbet": 4.9, "ladbrokes": 4.4, "tab": 5.0, "dabble": 5.0}, "best": {"price": 5.0, "book": "tab"}, "ev": 0.4242, "edge": 0.0848}, {"id": "sb|1-2", "label": "Juan Bautista Torres 2-1", "model": 0.2656, "fair": 3.76, "books": {"sportsbet": 5.5, "ladbrokes": 5.75, "tab": 5.0, "dabble": 5.0}, "best": {"price": 5.75, "book": "ladbrokes"}, "ev": 0.5274, "edge": 0.0917}, {"id": "sb|2-0", "label": "Marc Andrea Huesler 2-0", "model": 0.2174, "fair": 4.6, "books": {"sportsbet": 2.08, "ladbrokes": 1.94, "tab": 2.15, "dabble": 2.15}, "best": {"price": 2.15, "book": "tab"}, "ev": -0.5325, "edge": -0.2477}, {"id": "sb|2-1", "label": "Marc Andrea Huesler 2-1", "model": 0.2321, "fair": 4.31, "books": {"sportsbet": 3.75, "ladbrokes": 3.9, "tab": 3.4, "dabble": 3.5}, "best": {"price": 3.9, "book": "ladbrokes"}, "ev": -0.0949, "edge": -0.0243}]}, {"key": "sh", "label": "Set handicap", "selections": [{"id": "sh|1|-1.5", "label": "Marc Andrea Huesler -1.5 sets", "model": 0.2174, "fair": 4.6, "books": {"sportsbet": 2.05, "dabble": 2.2}, "best": {"price": 2.2, "book": "dabble"}, "ev": -0.5217, "edge": -0.2371}, {"id": "sh|1|1.5", "label": "Marc Andrea Huesler +1.5 sets", "model": 0.7152, "fair": 1.4, "books": {"sportsbet": 1.12}, "best": {"price": 1.12, "book": "sportsbet"}, "ev": -0.199, "edge": -0.1777}, {"id": "sh|2|-1.5", "label": "Juan Bautista Torres -1.5 sets", "model": 0.2848, "fair": 3.51, "books": {"sportsbet": 5.0}, "best": {"price": 5.0, "book": "sportsbet"}, "ev": 0.4242, "edge": 0.0848}, {"id": "sh|2|1.5", "label": "Juan Bautista Torres +1.5 sets", "model": 0.7826, "fair": 1.28, "books": {"sportsbet": 1.66, "dabble": 1.62}, "best": {"price": 1.66, "book": "sportsbet"}, "ev": 0.2991, "edge": 0.1802}]}, {"key": "pg", "label": "Player games", "selections": [{"id": "pg|1|O|12.5", "label": "Marc Andrea Huesler games Over 12.5", "model": 0.527, "fair": 1.9, "books": {"sportsbet": 1.88}, "best": {"price": 1.88, "book": "sportsbet"}, "ev": -0.0092, "edge": -0.0049}, {"id": "pg|1|U|12.5", "label": "Marc Andrea Huesler games Under 12.5", "model": 0.473, "fair": 2.11, "books": {"sportsbet": 1.85}, "best": {"price": 1.85, "book": "sportsbet"}, "ev": -0.125, "edge": -0.0675}, {"id": "pg|2|O|11.5", "label": "Juan Bautista Torres games Over 11.5", "model": 0.8023, "fair": 1.25, "books": {"sportsbet": 1.87}, "best": {"price": 1.87, "book": "sportsbet"}, "ev": 0.5003, "edge": 0.2675}, {"id": "pg|2|U|11.5", "label": "Juan Bautista Torres games Under 11.5", "model": 0.1977, "fair": 5.06, "books": {"sportsbet": 1.86}, "best": {"price": 1.86, "book": "sportsbet"}, "ev": -0.6323, "edge": -0.3399}]}]}, {"tour": "wta", "date": "", "tournament": "Livesport Prague Open", "round": "Round 2", "surface": "Hard", "player1": "Lucie Havlickova", "player2": "Barbora Krejcikova", "thin": true, "markets": [{"key": "mw", "label": "Match winner", "selections": [{"id": "mw|1", "label": "Lucie Havlickova", "model": 0.2374, "fair": 4.21, "books": {"sportsbet": 6.5, "ladbrokes": 6.0, "pointsbet": 6.5, "dabble": 6.5}, "best": {"price": 6.5, "book": "sportsbet"}, "ev": 0.5431, "edge": 0.0836}, {"id": "mw|2", "label": "Barbora Krejcikova", "model": 0.7626, "fair": 1.31, "books": {"sportsbet": 1.1, "ladbrokes": 1.11, "pointsbet": 1.1, "dabble": 1.11}, "best": {"price": 1.11, "book": "ladbrokes"}, "ev": -0.1535, "edge": -0.1383}]}, {"key": "sb", "label": "Set betting", "selections": [{"id": "sb|0-2", "label": "Barbora Krejcikova 2-0", "model": 0.1479, "fair": 6.76, "books": {"sportsbet": 1.35, "ladbrokes": 1.35, "pointsbet": 1.4, "dabble": 1.35}, "best": {"price": 1.4, "book": "pointsbet"}, "ev": -0.7929, "edge": -0.5664}, {"id": "sb|1-2", "label": "Barbora Krejcikova 2-1", "model": 0.1821, "fair": 5.49, "books": {"sportsbet": 4.8, "ladbrokes": 4.5, "pointsbet": 4.5, "dabble": 5.5}, "best": {"price": 5.5, "book": "dabble"}, "ev": 0.0014, "edge": 0.0003}, {"id": "sb|2-0", "label": "Lucie Havlickova 2-0", "model": 0.3787, "fair": 2.64, "books": {"sportsbet": 10.0, "ladbrokes": 9.25, "pointsbet": 11.0, "dabble": 11.0}, "best": {"price": 11.0, "book": "pointsbet"}, "ev": 3.1656, "edge": 0.2878}, {"id": "sb|2-1", "label": "Lucie Havlickova 2-1", "model": 0.2913, "fair": 3.43, "books": {"sportsbet": 9.5, "ladbrokes": 12.5, "pointsbet": 11.0, "dabble": 11.0}, "best": {"price": 12.5, "book": "ladbrokes"}, "ev": 2.6413, "edge": 0.2113}]}, {"key": "s1", "label": "1st set winner", "selections": [{"id": "s1|1", "label": "Lucie Havlickova", "model": 0.6154, "fair": 1.63, "books": {"pointsbet": 4.5}, "best": {"price": 4.5, "book": "pointsbet"}, "ev": 1.7692, "edge": 0.3932}, {"id": "s1|2", "label": "Barbora Krejcikova", "model": 0.3846, "fair": 2.6, "books": {"pointsbet": 1.18}, "best": {"price": 1.18, "book": "pointsbet"}, "ev": -0.5461, "edge": -0.4628}]}, {"key": "s2", "label": "2nd set winner", "selections": [{"id": "s2|1", "label": "Lucie Havlickova", "model": 0.6154, "fair": 1.63, "books": {"pointsbet": 4.5}, "best": {"price": 4.5, "book": "pointsbet"}, "ev": 1.7692, "edge": 0.3932}, {"id": "s2|2", "label": "Barbora Krejcikova", "model": 0.3846, "fair": 2.6, "books": {"pointsbet": 1.18}, "best": {"price": 1.18, "book": "pointsbet"}, "ev": -0.5461, "edge": -0.4628}]}, {"key": "tg", "label": "Total games", "selections": [{"id": "tg|O|17.5", "label": "Over 17.5", "model": 0.8626, "fair": 1.16, "books": {"pointsbet": 1.57}, "best": {"price": 1.57, "book": "pointsbet"}, "ev": 0.3543, "edge": 0.2257}, {"id": "tg|O|18.5", "label": "Over 18.5", "model": 0.7967, "fair": 1.26, "books": {"pointsbet": 1.85}, "best": {"price": 1.85, "book": "pointsbet"}, "ev": 0.4739, "edge": 0.2562}, {"id": "tg|O|19.5", "label": "Over 19.5", "model": 0.7169, "fair": 1.39, "books": {"pointsbet": 2.15}, "best": {"price": 2.15, "book": "pointsbet"}, "ev": 0.5414, "edge": 0.2518}, {"id": "tg|U|17.5", "label": "Under 17.5", "model": 0.1374, "fair": 7.28, "books": {"pointsbet": 2.3}, "best": {"price": 2.3, "book": "pointsbet"}, "ev": -0.684, "edge": -0.2974}, {"id": "tg|U|18.5", "label": "Under 18.5", "model": 0.2033, "fair": 4.92, "books": {"pointsbet": 1.89}, "best": {"price": 1.89, "book": "pointsbet"}, "ev": -0.6158, "edge": -0.3258}, {"id": "tg|U|19.5", "label": "Under 19.5", "model": 0.2831, "fair": 3.53, "books": {"pointsbet": 1.65}, "best": {"price": 1.65, "book": "pointsbet"}, "ev": -0.5329, "edge": -0.323}]}, {"key": "gh", "label": "Games handicap", "selections": [{"id": "gh|1|4.5", "label": "Lucie Havlickova +4.5", "model": 0.8829, "fair": 1.13, "books": {"pointsbet": 2.9}, "best": {"price": 2.9, "book": "pointsbet"}, "ev": 1.5603, "edge": 0.538}, {"id": "gh|1|5.5", "label": "Lucie Havlickova +5.5", "model": 0.9313, "fair": 1.07, "books": {"pointsbet": 2.2}, "best": {"price": 2.2, "book": "pointsbet"}, "ev": 1.0488, "edge": 0.4767}, {"id": "gh|1|6.5", "label": "Lucie Havlickova +6.5", "model": 0.9631, "fair": 1.04, "books": {"pointsbet": 1.68}, "best": {"price": 1.68, "book": "pointsbet"}, "ev": 0.618, "edge": 0.3679}, {"id": "gh|2|-4.5", "label": "Barbora Krejcikova -4.5", "model": 0.1171, "fair": 8.54, "books": {"pointsbet": 1.38}, "best": {"price": 1.38, "book": "pointsbet"}, "ev": -0.8384, "edge": -0.6075}, {"id": "gh|2|-5.5", "label": "Barbora Krejcikova -5.5", "model": 0.0687, "fair": 14.55, "books": {"pointsbet": 1.63}, "best": {"price": 1.63, "book": "pointsbet"}, "ev": -0.888, "edge": -0.5448}, {"id": "gh|2|-6.5", "label": "Barbora Krejcikova -6.5", "model": 0.0369, "fair": 27.09, "books": {"pointsbet": 2.1}, "best": {"price": 2.1, "book": "pointsbet"}, "ev": -0.9225, "edge": -0.4393}]}, {"key": "sh", "label": "Set handicap", "selections": [{"id": "sh|1|-1.5", "label": "Lucie Havlickova -1.5 sets", "model": 0.3787, "fair": 2.64, "books": {"sportsbet": 11.0, "pointsbet": 10.0, "dabble": 13.0}, "best": {"price": 13.0, "book": "dabble"}, "ev": 3.923, "edge": 0.3018}, {"id": "sh|1|1.5", "label": "Lucie Havlickova +1.5 sets", "model": 0.8521, "fair": 1.17, "books": {"sportsbet": 3.0, "pointsbet": 2.8, "dabble": 3.1}, "best": {"price": 3.1, "book": "dabble"}, "ev": 1.6414, "edge": 0.5295}, {"id": "sh|2|-1.5", "label": "Barbora Krejcikova -1.5 sets", "model": 0.1479, "fair": 6.76, "books": {"sportsbet": 1.33, "pointsbet": 1.39, "dabble": 1.35}, "best": {"price": 1.39, "book": "pointsbet"}, "ev": -0.7944, "edge": -0.5715}, {"id": "sh|2|1.5", "label": "Barbora Krejcikova +1.5 sets", "model": 0.6213, "fair": 1.61, "books": {"sportsbet": 1.01, "pointsbet": 1.03, "dabble": 1.04}, "best": {"price": 1.04, "book": "dabble"}, "ev": -0.3538, "edge": -0.3402}]}, {"key": "pg", "label": "Player games", "selections": [{"id": "pg|2|O|12.5", "label": "Barbora Krejcikova games Over 12.5", "model": 0.5693, "fair": 1.76, "books": {"sportsbet": 2.25}, "best": {"price": 2.25, "book": "sportsbet"}, "ev": 0.2809, "edge": 0.1249}, {"id": "pg|2|U|12.5", "label": "Barbora Krejcikova games Under 12.5", "model": 0.4307, "fair": 2.32, "books": {"sportsbet": 1.57}, "best": {"price": 1.57, "book": "sportsbet"}, "ev": -0.3238, "edge": -0.2062}]}, {"key": "ma", "label": "Most aces", "selections": [{"id": "ma|1", "label": "Lucie Havlickova most aces", "model": 0.3458, "fair": 2.89, "books": {"dabble": 2.8}, "best": {"price": 2.8, "book": "dabble"}, "ev": -0.0318, "edge": -0.0113}, {"id": "ma|2", "label": "Barbora Krejcikova most aces", "model": 0.5078, "fair": 1.97, "books": {"dabble": 1.53}, "best": {"price": 1.53, "book": "dabble"}, "ev": -0.2231, "edge": -0.1458}, {"id": "ma|tie", "label": "Most aces — tie", "model": 0.1464, "fair": 6.83, "books": {"dabble": 4.0}, "best": {"price": 4.0, "book": "dabble"}, "ev": -0.4144, "edge": -0.1036}]}]}, {"tour": "wta", "date": "", "tournament": "Hamburg", "round": "Round 2", "surface": "Clay", "player1": "Paula Badosa", "player2": "Panna Udvardy", "thin": false, "markets": [{"key": "mw", "label": "Match winner", "selections": [{"id": "mw|1", "label": "Paula Badosa", "model": 0.5674, "fair": 1.76, "books": {"sportsbet": 1.52, "ladbrokes": 1.58, "pointsbet": 1.6}, "best": {"price": 1.6, "book": "pointsbet"}, "ev": -0.0922, "edge": -0.0576}, {"id": "mw|2", "label": "Panna Udvardy", "model": 0.4326, "fair": 2.31, "books": {"sportsbet": 2.42, "ladbrokes": 2.3, "pointsbet": 2.3}, "best": {"price": 2.42, "book": "sportsbet"}, "ev": 0.0469, "edge": 0.0194}]}, {"key": "sb", "label": "Set betting", "selections": [{"id": "sb|0-2", "label": "Panna Udvardy 2-0", "model": 0.106, "fair": 9.44, "books": {"sportsbet": 4.0, "ladbrokes": 3.5, "pointsbet": 3.9}, "best": {"price": 4.0, "book": "sportsbet"}, "ev": -0.5762, "edge": -0.144}, {"id": "sb|1-2", "label": "Panna Udvardy 2-1", "model": 0.1429, "fair": 7.0, "books": {"sportsbet": 5.1, "ladbrokes": 5.0, "pointsbet": 5.25}, "best": {"price": 5.25, "book": "pointsbet"}, "ev": -0.2496, "edge": -0.0475}, {"id": "sb|2-0", "label": "Paula Badosa 2-0", "model": 0.4549, "fair": 2.2, "books": {"sportsbet": 2.4, "ladbrokes": 2.2, "pointsbet": 2.3}, "best": {"price": 2.4, "book": "sportsbet"}, "ev": 0.0918, "edge": 0.0383}, {"id": "sb|2-1", "label": "Paula Badosa 2-1", "model": 0.2962, "fair": 3.38, "books": {"sportsbet": 3.8, "ladbrokes": 4.0, "pointsbet": 4.0}, "best": {"price": 4.0, "book": "ladbrokes"}, "ev": 0.1847, "edge": 0.0462}]}, {"key": "s1", "label": "1st set winner", "selections": [{"id": "s1|1", "label": "Paula Badosa", "model": 0.6745, "fair": 1.48, "books": {"pointsbet": 1.63}, "best": {"price": 1.63, "book": "pointsbet"}, "ev": 0.0994, "edge": 0.061}, {"id": "s1|2", "label": "Panna Udvardy", "model": 0.3255, "fair": 3.07, "books": {"pointsbet": 2.2}, "best": {"price": 2.2, "book": "pointsbet"}, "ev": -0.2839, "edge": -0.129}]}, {"key": "s2", "label": "2nd set winner", "selections": [{"id": "s2|1", "label": "Paula Badosa", "model": 0.6745, "fair": 1.48, "books": {"pointsbet": 1.63}, "best": {"price": 1.63, "book": "pointsbet"}, "ev": 0.0994, "edge": 0.061}, {"id": "s2|2", "label": "Panna Udvardy", "model": 0.3255, "fair": 3.07, "books": {"pointsbet": 2.2}, "best": {"price": 2.2, "book": "pointsbet"}, "ev": -0.2839, "edge": -0.129}]}, {"key": "tg", "label": "Total games", "selections": [{"id": "tg|O|20.5", "label": "Over 20.5", "model": 0.6299, "fair": 1.59, "books": {"pointsbet": 1.75}, "best": {"price": 1.75, "book": "pointsbet"}, "ev": 0.1023, "edge": 0.0585}, {"id": "tg|O|21.5", "label": "Over 21.5", "model": 0.577, "fair": 1.73, "books": {"pointsbet": 1.91}, "best": {"price": 1.91, "book": "pointsbet"}, "ev": 0.102, "edge": 0.0534}, {"id": "tg|O|22.5", "label": "Over 22.5", "model": 0.5085, "fair": 1.97, "books": {"pointsbet": 2.2}, "best": {"price": 2.2, "book": "pointsbet"}, "ev": 0.1187, "edge": 0.054}, {"id": "tg|U|20.5", "label": "Under 20.5", "model": 0.3701, "fair": 2.7, "books": {"pointsbet": 2.0}, "best": {"price": 2.0, "book": "pointsbet"}, "ev": -0.2598, "edge": -0.1299}, {"id": "tg|U|21.5", "label": "Under 21.5", "model": 0.423, "fair": 2.36, "books": {"pointsbet": 1.83}, "best": {"price": 1.83, "book": "pointsbet"}, "ev": -0.2258, "edge": -0.1234}, {"id": "tg|U|22.5", "label": "Under 22.5", "model": 0.4915, "fair": 2.03, "books": {"pointsbet": 1.63}, "best": {"price": 1.63, "book": "pointsbet"}, "ev": -0.1989, "edge": -0.122}]}, {"key": "gh", "label": "Games handicap", "selections": [{"id": "gh|1|-1.5", "label": "Paula Badosa -1.5", "model": 0.6997, "fair": 1.43, "books": {"pointsbet": 1.7}, "best": {"price": 1.7, "book": "pointsbet"}, "ev": 0.1895, "edge": 0.1114}, {"id": "gh|1|-2.5", "label": "Paula Badosa -2.5", "model": 0.6416, "fair": 1.56, "books": {"pointsbet": 1.83}, "best": {"price": 1.83, "book": "pointsbet"}, "ev": 0.1741, "edge": 0.0951}, {"id": "gh|1|-3.5", "label": "Paula Badosa -3.5", "model": 0.5458, "fair": 1.83, "books": {"pointsbet": 2.05}, "best": {"price": 2.05, "book": "pointsbet"}, "ev": 0.1189, "edge": 0.058}, {"id": "gh|2|1.5", "label": "Panna Udvardy +1.5", "model": 0.3003, "fair": 3.33, "books": {"pointsbet": 2.08}, "best": {"price": 2.08, "book": "pointsbet"}, "ev": -0.3753, "edge": -0.1805}, {"id": "gh|2|2.5", "label": "Panna Udvardy +2.5", "model": 0.3584, "fair": 2.79, "books": {"pointsbet": 1.91}, "best": {"price": 1.91, "book": "pointsbet"}, "ev": -0.3155, "edge": -0.1652}, {"id": "gh|2|3.5", "label": "Panna Udvardy +3.5", "model": 0.4542, "fair": 2.2, "books": {"pointsbet": 1.72}, "best": {"price": 1.72, "book": "pointsbet"}, "ev": -0.2188, "edge": -0.1272}]}, {"key": "sh", "label": "Set handicap", "selections": [{"id": "sh|1|-1.5", "label": "Paula Badosa -1.5 sets", "model": 0.4549, "fair": 2.2, "books": {"sportsbet": 2.4, "pointsbet": 2.32}, "best": {"price": 2.4, "book": "sportsbet"}, "ev": 0.0918, "edge": 0.0383}, {"id": "sh|1|1.5", "label": "Paula Badosa +1.5 sets", "model": 0.894, "fair": 1.12, "books": {"sportsbet": 1.2, "pointsbet": 1.24}, "best": {"price": 1.24, "book": "pointsbet"}, "ev": 0.1086, "edge": 0.0876}, {"id": "sh|2|-1.5", "label": "Panna Udvardy -1.5 sets", "model": 0.106, "fair": 9.44, "books": {"sportsbet": 4.0, "pointsbet": 3.7}, "best": {"price": 4.0, "book": "sportsbet"}, "ev": -0.5762, "edge": -0.144}, {"id": "sh|2|1.5", "label": "Panna Udvardy +1.5 sets", "model": 0.5451, "fair": 1.83, "books": {"sportsbet": 1.5, "pointsbet": 1.56}, "best": {"price": 1.56, "book": "pointsbet"}, "ev": -0.1497, "edge": -0.096}]}, {"key": "pg", "label": "Player games", "selections": [{"id": "pg|1|O|12.5", "label": "Paula Badosa games Over 12.5", "model": 0.5684, "fair": 1.76, "books": {"sportsbet": 2.0}, "best": {"price": 2.0, "book": "sportsbet"}, "ev": 0.1368, "edge": 0.0684}, {"id": "pg|1|U|12.5", "label": "Paula Badosa games Under 12.5", "model": 0.4316, "fair": 2.32, "books": {"sportsbet": 1.72}, "best": {"price": 1.72, "book": "sportsbet"}, "ev": -0.2576, "edge": -0.1498}, {"id": "pg|2|O|11.5", "label": "Panna Udvardy games Over 11.5", "model": 0.6511, "fair": 1.54, "books": {"sportsbet": 1.65}, "best": {"price": 1.65, "book": "sportsbet"}, "ev": 0.0743, "edge": 0.045}, {"id": "pg|2|U|11.5", "label": "Panna Udvardy games Under 11.5", "model": 0.3489, "fair": 2.87, "books": {"sportsbet": 2.1}, "best": {"price": 2.1, "book": "sportsbet"}, "ev": -0.2673, "edge": -0.1273}]}, {"key": "pa", "label": "Player aces", "selections": [{"id": "pa|1|O|4.5", "label": "Paula Badosa aces Over 4.5", "model": 0.1276, "fair": 7.84, "books": {"sportsbet": 1.72}, "best": {"price": 1.72, "book": "sportsbet"}, "ev": -0.7805, "edge": -0.4538}, {"id": "pa|1|U|4.5", "label": "Paula Badosa aces Under 4.5", "model": 0.8724, "fair": 1.15, "books": {"sportsbet": 2.0}, "best": {"price": 2.0, "book": "sportsbet"}, "ev": 0.7448, "edge": 0.3724}, {"id": "pa|2|O|1.5", "label": "Panna Udvardy aces Over 1.5", "model": 0.5989, "fair": 1.67, "books": {"sportsbet": 1.95}, "best": {"price": 1.95, "book": "sportsbet"}, "ev": 0.1679, "edge": 0.0861}, {"id": "pa|2|U|1.5", "label": "Panna Udvardy aces Under 1.5", "model": 0.4011, "fair": 2.49, "books": {"sportsbet": 1.75}, "best": {"price": 1.75, "book": "sportsbet"}, "ev": -0.2981, "edge": -0.1703}]}]}, {"tour": "atp", "date": "20260723", "tournament": "Millennium Estoril Open", "round": "Round 2", "surface": "Hard", "player1": "Timofey Skatov", "player2": "Andrey Rublev", "thin": false, "markets": [{"key": "mw", "label": "Match winner", "selections": [{"id": "mw|1", "label": "Timofey Skatov", "model": 0.1801, "fair": 5.55, "books": {"sportsbet": 10.0, "ladbrokes": 9.75, "dabble": 9.0}, "best": {"price": 10.0, "book": "sportsbet"}, "ev": 0.801, "edge": 0.0801}, {"id": "mw|2", "label": "Andrey Rublev", "model": 0.8199, "fair": 1.22, "books": {"sportsbet": 1.03, "ladbrokes": 1.04, "dabble": 1.07}, "best": {"price": 1.07, "book": "dabble"}, "ev": -0.1227, "edge": -0.1147}]}, {"key": "sb", "label": "Set betting", "selections": [{"id": "sb|0-2", "label": "Andrey Rublev 2-0", "model": 0.4033, "fair": 2.48, "books": {"sportsbet": 1.2, "ladbrokes": 1.2, "dabble": 1.26}, "best": {"price": 1.26, "book": "dabble"}, "ev": -0.4919, "edge": -0.3904}, {"id": "sb|1-2", "label": "Andrey Rublev 2-1", "model": 0.2944, "fair": 3.4, "books": {"sportsbet": 5.25, "ladbrokes": 5.6, "dabble": 5.5}, "best": {"price": 5.6, "book": "ladbrokes"}, "ev": 0.6484, "edge": 0.1158}, {"id": "sb|2-0", "label": "Timofey Skatov 2-0", "model": 0.1332, "fair": 7.51, "books": {"sportsbet": 17.0, "ladbrokes": 14.0, "dabble": 19.0}, "best": {"price": 19.0, "book": "dabble"}, "ev": 1.5309, "edge": 0.0806}, {"id": "sb|2-1", "label": "Timofey Skatov 2-1", "model": 0.1692, "fair": 5.91, "books": {"sportsbet": 14.0, "ladbrokes": 19.0, "dabble": 15.0}, "best": {"price": 19.0, "book": "ladbrokes"}, "ev": 2.2144, "edge": 0.1165}]}, {"key": "tg", "label": "Total games", "selections": [{"id": "tg|O|18.5", "label": "Over 18.5", "model": 0.8803, "fair": 1.14, "books": {"dabble": 1.88}, "best": {"price": 1.88, "book": "dabble"}, "ev": 0.655, "edge": 0.3484}, {"id": "tg|U|18.5", "label": "Under 18.5", "model": 0.1197, "fair": 8.35, "books": {"dabble": 1.88}, "best": {"price": 1.88, "book": "dabble"}, "ev": -0.775, "edge": -0.4122}]}, {"key": "gh", "label": "Games handicap", "selections": [{"id": "gh|1|6.5", "label": "Timofey Skatov +6.5", "model": 0.9226, "fair": 1.08, "books": {"dabble": 1.7}, "best": {"price": 1.7, "book": "dabble"}, "ev": 0.5684, "edge": 0.3343}, {"id": "gh|2|-6.5", "label": "Andrey Rublev -6.5", "model": 0.0774, "fair": 12.92, "books": {"dabble": 2.08}, "best": {"price": 2.08, "book": "dabble"}, "ev": -0.839, "edge": -0.4033}]}, {"key": "sh", "label": "Set handicap", "selections": [{"id": "sh|1|-1.5", "label": "Timofey Skatov -1.5 sets", "model": 0.1332, "fair": 7.51, "books": {"dabble": 17.0}, "best": {"price": 17.0, "book": "dabble"}, "ev": 1.2645, "edge": 0.0744}, {"id": "sh|1|1.5", "label": "Timofey Skatov +1.5 sets", "model": 0.5967, "fair": 1.68, "books": {"dabble": 3.6}, "best": {"price": 3.6, "book": "dabble"}, "ev": 1.1483, "edge": 0.319}, {"id": "sh|2|-1.5", "label": "Andrey Rublev -1.5 sets", "model": 0.4033, "fair": 2.48, "books": {"dabble": 1.25}, "best": {"price": 1.25, "book": "dabble"}, "ev": -0.4959, "edge": -0.3967}, {"id": "sh|2|1.5", "label": "Andrey Rublev +1.5 sets", "model": 0.8668, "fair": 1.15, "books": {"dabble": 1.02}, "best": {"price": 1.02, "book": "dabble"}, "ev": -0.1159, "edge": -0.1136}]}, {"key": "pg", "label": "Player games", "selections": [{"id": "pg|2|O|12.5", "label": "Andrey Rublev games Over 12.5", "model": 0.6312, "fair": 1.58, "books": {"dabble": 2.4}, "best": {"price": 2.4, "book": "dabble"}, "ev": 0.5149, "edge": 0.2145}, {"id": "pg|2|U|12.5", "label": "Andrey Rublev games Under 12.5", "model": 0.3688, "fair": 2.71, "books": {"dabble": 1.52}, "best": {"price": 1.52, "book": "dabble"}, "ev": -0.4394, "edge": -0.2891}]}, {"key": "ma", "label": "Most aces", "selections": [{"id": "ma|1", "label": "Timofey Skatov most aces", "model": 0.136, "fair": 7.35, "books": {"dabble": 5.0}, "best": {"price": 5.0, "book": "dabble"}, "ev": -0.32, "edge": -0.064}, {"id": "ma|2", "label": "Andrey Rublev most aces", "model": 0.7967, "fair": 1.26, "books": {"dabble": 1.01}, "best": {"price": 1.01, "book": "dabble"}, "ev": -0.1953, "edge": -0.1934}, {"id": "ma|tie", "label": "Most aces — tie", "model": 0.0672, "fair": 14.88, "books": {"dabble": 5.0}, "best": {"price": 5.0, "book": "dabble"}, "ev": -0.664, "edge": -0.1328}]}]}, {"tour": "atp", "date": "20260723", "tournament": "Generali Open", "round": "Quarterfinal", "surface": "Hard", "player1": "Alex Molcan", "player2": "Alexander Bublik", "thin": false, "markets": [{"key": "mw", "label": "Match winner", "selections": [{"id": "mw|1", "label": "Alex Molcan", "model": 0.3673, "fair": 2.72, "books": {"sportsbet": 2.34, "ladbrokes": 2.3, "dabble": 2.25}, "best": {"price": 2.34, "book": "sportsbet"}, "ev": -0.1405, "edge": -0.0601}, {"id": "mw|2", "label": "Alexander Bublik", "model": 0.6327, "fair": 1.58, "books": {"sportsbet": 1.56, "ladbrokes": 1.58, "dabble": 1.64}, "best": {"price": 1.64, "book": "dabble"}, "ev": 0.0376, "edge": 0.0229}]}, {"key": "sb", "label": "Set betting", "selections": [{"id": "sb|0-2", "label": "Alexander Bublik 2-0", "model": 0.176, "fair": 5.68, "books": {"sportsbet": 2.45, "ladbrokes": 2.3, "dabble": 2.65}, "best": {"price": 2.65, "book": "dabble"}, "ev": -0.5337, "edge": -0.2014}, {"id": "sb|1-2", "label": "Alexander Bublik 2-1", "model": 0.2043, "fair": 4.89, "books": {"sportsbet": 3.75, "ladbrokes": 3.8, "dabble": 3.85}, "best": {"price": 3.85, "book": "dabble"}, "ev": -0.2134, "edge": -0.0554}, {"id": "sb|2-0", "label": "Alex Molcan 2-0", "model": 0.337, "fair": 2.97, "books": {"sportsbet": 3.9, "ladbrokes": 3.6, "dabble": 3.85}, "best": {"price": 3.9, "book": "sportsbet"}, "ev": 0.3143, "edge": 0.0806}, {"id": "sb|2-1", "label": "Alex Molcan 2-1", "model": 0.2827, "fair": 3.54, "books": {"sportsbet": 4.9, "ladbrokes": 4.75, "dabble": 4.4}, "best": {"price": 4.9, "book": "sportsbet"}, "ev": 0.3854, "edge": 0.0786}]}, {"key": "tg", "label": "Total games", "selections": [{"id": "tg|O|23.5", "label": "Over 23.5", "model": 0.5461, "fair": 1.83, "books": {"dabble": 1.98}, "best": {"price": 1.98, "book": "dabble"}, "ev": 0.0813, "edge": 0.041}, {"id": "tg|U|23.5", "label": "Under 23.5", "model": 0.4539, "fair": 2.2, "books": {"dabble": 1.8}, "best": {"price": 1.8, "book": "dabble"}, "ev": -0.183, "edge": -0.1017}]}, {"key": "gh", "label": "Games handicap", "selections": [{"id": "gh|1|1.5", "label": "Alex Molcan +1.5", "model": 0.7011, "fair": 1.43, "books": {"dabble": 1.95}, "best": {"price": 1.95, "book": "dabble"}, "ev": 0.3671, "edge": 0.1883}, {"id": "gh|2|-1.5", "label": "Alexander Bublik -1.5", "model": 0.2989, "fair": 3.35, "books": {"dabble": 1.8}, "best": {"price": 1.8, "book": "dabble"}, "ev": -0.462, "edge": -0.2567}]}, {"key": "sh", "label": "Set handicap", "selections": [{"id": "sh|1|-1.5", "label": "Alex Molcan -1.5 sets", "model": 0.337, "fair": 2.97, "books": {"sportsbet": 3.9, "dabble": 3.85}, "best": {"price": 3.9, "book": "sportsbet"}, "ev": 0.3143, "edge": 0.0806}, {"id": "sh|1|1.5", "label": "Alex Molcan +1.5 sets", "model": 0.824, "fair": 1.21, "books": {"dabble": 1.45}, "best": {"price": 1.45, "book": "dabble"}, "ev": 0.1948, "edge": 0.1344}, {"id": "sh|2|-1.5", "label": "Alexander Bublik -1.5 sets", "model": 0.176, "fair": 5.68, "books": {"dabble": 2.55}, "best": {"price": 2.55, "book": "dabble"}, "ev": -0.5513, "edge": -0.2162}, {"id": "sh|2|1.5", "label": "Alexander Bublik +1.5 sets", "model": 0.663, "fair": 1.51, "books": {"sportsbet": 1.2, "dabble": 1.22}, "best": {"price": 1.22, "book": "dabble"}, "ev": -0.1911, "edge": -0.1567}]}, {"key": "pg", "label": "Player games", "selections": [{"id": "pg|1|O|12.5", "label": "Alex Molcan games Over 12.5", "model": 0.5355, "fair": 1.87, "books": {"sportsbet": 1.94, "dabble": 1.9}, "best": {"price": 1.94, "book": "sportsbet"}, "ev": 0.0389, "edge": 0.02}, {"id": "pg|1|U|12.5", "label": "Alex Molcan games Under 12.5", "model": 0.4645, "fair": 2.15, "books": {"sportsbet": 1.8, "dabble": 1.82}, "best": {"price": 1.82, "book": "dabble"}, "ev": -0.1546, "edge": -0.085}, {"id": "pg|2|O|12.5", "label": "Alexander Bublik games Over 12.5", "model": 0.6366, "fair": 1.57, "books": {"sportsbet": 1.63, "dabble": 1.67}, "best": {"price": 1.67, "book": "dabble"}, "ev": 0.0631, "edge": 0.0378}, {"id": "pg|2|U|12.5", "label": "Alexander Bublik games Under 12.5", "model": 0.3634, "fair": 2.75, "books": {"sportsbet": 2.18, "dabble": 2.1}, "best": {"price": 2.18, "book": "sportsbet"}, "ev": -0.2078, "edge": -0.0953}]}, {"key": "pa", "label": "Player aces", "selections": [{"id": "pa|2|O|10.5", "label": "Alexander Bublik aces Over 10.5", "model": 0.459, "fair": 2.18, "books": {"sportsbet": 1.88}, "best": {"price": 1.88, "book": "sportsbet"}, "ev": -0.1371, "edge": -0.0729}, {"id": "pa|2|U|10.5", "label": "Alexander Bublik aces Under 10.5", "model": 0.541, "fair": 1.85, "books": {"sportsbet": 1.85}, "best": {"price": 1.85, "book": "sportsbet"}, "ev": 0.0009, "edge": 0.0005}]}, {"key": "ma", "label": "Most aces", "selections": [{"id": "ma|1", "label": "Alex Molcan most aces", "model": 0.1326, "fair": 7.54, "books": {"dabble": 23.0}, "best": {"price": 23.0, "book": "dabble"}, "ev": 2.0498, "edge": 0.0891}, {"id": "ma|tie", "label": "Most aces — tie", "model": 0.0613, "fair": 16.31, "books": {"dabble": 23.0}, "best": {"price": 23.0, "book": "dabble"}, "ev": 0.4099, "edge": 0.0178}]}, {"key": "md", "label": "Most double faults", "selections": [{"id": "md|1", "label": "Alex Molcan most double faults", "model": 0.1599, "fair": 6.25, "books": {"dabble": 3.3}, "best": {"price": 3.3, "book": "dabble"}, "ev": -0.4723, "edge": -0.1431}, {"id": "md|2", "label": "Alexander Bublik most double faults", "model": 0.732, "fair": 1.37, "books": {"dabble": 1.21}, "best": {"price": 1.21, "book": "dabble"}, "ev": -0.1143, "edge": -0.0944}, {"id": "md|tie", "label": "Most double faults — tie", "model": 0.1081, "fair": 9.25, "books": {"dabble": 3.9}, "best": {"price": 3.9, "book": "dabble"}, "ev": -0.5784, "edge": -0.1483}]}]}, {"tour": "atp", "date": "20260723", "tournament": "Millennium Estoril Open", "round": "Round 2", "surface": "Hard", "player1": "Luciano Darderi", "player2": "Pedro Martinez", "thin": false, "markets": [{"key": "mw", "label": "Match winner", "selections": [{"id": "mw|1", "label": "Luciano Darderi", "model": 0.6309, "fair": 1.59, "books": {"sportsbet": 1.28, "ladbrokes": 1.3}, "best": {"price": 1.3, "book": "ladbrokes"}, "ev": -0.1798, "edge": -0.1383}, {"id": "mw|2", "label": "Pedro Martinez", "model": 0.3691, "fair": 2.71, "books": {"sportsbet": 3.25, "ladbrokes": 3.35}, "best": {"price": 3.35, "book": "ladbrokes"}, "ev": 0.2365, "edge": 0.0706}]}, {"key": "sb", "label": "Set betting", "selections": [{"id": "sb|0-2", "label": "Pedro Martinez 2-0", "model": 0.206, "fair": 4.85, "books": {"sportsbet": 6.0, "ladbrokes": 5.5}, "best": {"price": 6.0, "book": "sportsbet"}, "ev": 0.2359, "edge": 0.0393}, {"id": "sb|1-2", "label": "Pedro Martinez 2-1", "model": 0.225, "fair": 4.44, "books": {"sportsbet": 6.25, "ladbrokes": 6.6}, "best": {"price": 6.6, "book": "ladbrokes"}, "ev": 0.485, "edge": 0.0735}, {"id": "sb|2-0", "label": "Luciano Darderi 2-0", "model": 0.2983, "fair": 3.35, "books": {"sportsbet": 1.86, "ladbrokes": 1.7}, "best": {"price": 1.86, "book": "sportsbet"}, "ev": -0.4452, "edge": -0.2394}, {"id": "sb|2-1", "label": "Luciano Darderi 2-1", "model": 0.2707, "fair": 3.69, "books": {"sportsbet": 3.5, "ladbrokes": 4.0}, "best": {"price": 4.0, "book": "ladbrokes"}, "ev": 0.083, "edge": 0.0207}]}]}, {"tour": "atp", "date": "20260723", "tournament": "Generali Open", "round": "Quarterfinal", "surface": "Hard", "player1": "Sebastian Baez", "player2": "Yannick Hanfmann", "thin": false, "markets": [{"key": "mw", "label": "Match winner", "selections": [{"id": "mw|1", "label": "Sebastian Baez", "model": 0.397, "fair": 2.52, "books": {"sportsbet": 2.1, "dabble": 2.05}, "best": {"price": 2.1, "book": "sportsbet"}, "ev": -0.1663, "edge": -0.0792}, {"id": "mw|2", "label": "Yannick Hanfmann", "model": 0.603, "fair": 1.66, "books": {"sportsbet": 1.72, "dabble": 1.77}, "best": {"price": 1.77, "book": "dabble"}, "ev": 0.0673, "edge": 0.038}]}, {"key": "sb", "label": "Set betting", "selections": [{"id": "sb|0-2", "label": "Yannick Hanfmann 2-0", "model": 0.3306, "fair": 3.03, "books": {"sportsbet": 2.75, "dabble": 2.9}, "best": {"price": 2.9, "book": "dabble"}, "ev": -0.0414, "edge": -0.0143}, {"id": "sb|1-2", "label": "Yannick Hanfmann 2-1", "model": 0.281, "fair": 3.56, "books": {"sportsbet": 3.75, "dabble": 3.85}, "best": {"price": 3.85, "book": "dabble"}, "ev": 0.0819, "edge": 0.0213}, {"id": "sb|2-0", "label": "Sebastian Baez 2-0", "model": 0.1807, "fair": 5.53, "books": {"sportsbet": 3.5, "dabble": 3.4}, "best": {"price": 3.5, "book": "sportsbet"}, "ev": -0.3676, "edge": -0.105}, {"id": "sb|2-1", "label": "Sebastian Baez 2-1", "model": 0.2078, "fair": 4.81, "books": {"sportsbet": 4.7, "dabble": 4.5}, "best": {"price": 4.7, "book": "sportsbet"}, "ev": -0.0236, "edge": -0.005}]}, {"key": "tg", "label": "Total games", "selections": [{"id": "tg|O|23.5", "label": "Over 23.5", "model": 0.5286, "fair": 1.89, "books": {"dabble": 1.95}, "best": {"price": 1.95, "book": "dabble"}, "ev": 0.0308, "edge": 0.0158}, {"id": "tg|U|20.5", "label": "Under 20.5", "model": 0.2876, "fair": 3.48, "books": {"dabble": 3.1}, "best": {"price": 3.1, "book": "dabble"}, "ev": -0.1084, "edge": -0.035}, {"id": "tg|U|23.5", "label": "Under 23.5", "model": 0.4714, "fair": 2.12, "books": {"dabble": 1.82}, "best": {"price": 1.82, "book": "dabble"}, "ev": -0.1421, "edge": -0.0781}]}, {"key": "gh", "label": "Games handicap", "selections": [{"id": "gh|1|0.5", "label": "Sebastian Baez +0.5", "model": 0.4138, "fair": 2.42, "books": {"dabble": 1.9}, "best": {"price": 1.9, "book": "dabble"}, "ev": -0.2138, "edge": -0.1125}, {"id": "gh|2|-0.5", "label": "Yannick Hanfmann -0.5", "model": 0.5862, "fair": 1.71, "books": {"dabble": 1.85}, "best": {"price": 1.85, "book": "dabble"}, "ev": 0.0845, "edge": 0.0457}]}, {"key": "sh", "label": "Set handicap", "selections": [{"id": "sh|1|-1.5", "label": "Sebastian Baez -1.5 sets", "model": 0.1807, "fair": 5.53, "books": {"sportsbet": 3.7, "dabble": 3.3}, "best": {"price": 3.7, "book": "sportsbet"}, "ev": -0.3315, "edge": -0.0896}, {"id": "sh|1|1.5", "label": "Sebastian Baez +1.5 sets", "model": 0.6694, "fair": 1.49, "books": {"dabble": 1.38}, "best": {"price": 1.38, "book": "dabble"}, "ev": -0.0762, "edge": -0.0552}, {"id": "sh|2|-1.5", "label": "Yannick Hanfmann -1.5 sets", "model": 0.3306, "fair": 3.03, "books": {"dabble": 2.8}, "best": {"price": 2.8, "book": "dabble"}, "ev": -0.0744, "edge": -0.0266}, {"id": "sh|2|1.5", "label": "Yannick Hanfmann +1.5 sets", "model": 0.8193, "fair": 1.22, "books": {"sportsbet": 1.22, "dabble": 1.28}, "best": {"price": 1.28, "book": "dabble"}, "ev": 0.0487, "edge": 0.0381}]}, {"key": "pg", "label": "Player games", "selections": [{"id": "pg|1|O|12.5", "label": "Sebastian Baez games Over 12.5", "model": 0.5173, "fair": 1.93, "books": {"sportsbet": 1.92, "dabble": 1.78}, "best": {"price": 1.92, "book": "sportsbet"}, "ev": -0.0068, "edge": -0.0035}, {"id": "pg|1|U|12.5", "label": "Sebastian Baez games Under 12.5", "model": 0.4827, "fair": 2.07, "books": {"sportsbet": 1.81, "dabble": 1.95}, "best": {"price": 1.95, "book": "dabble"}, "ev": -0.0587, "edge": -0.0301}, {"id": "pg|2|O|12.5", "label": "Yannick Hanfmann games Over 12.5", "model": 0.592, "fair": 1.69, "books": {"sportsbet": 1.75, "dabble": 1.7}, "best": {"price": 1.75, "book": "sportsbet"}, "ev": 0.036, "edge": 0.0206}, {"id": "pg|2|U|12.5", "label": "Yannick Hanfmann games Under 12.5", "model": 0.408, "fair": 2.45, "books": {"sportsbet": 2.0, "dabble": 2.05}, "best": {"price": 2.05, "book": "dabble"}, "ev": -0.1636, "edge": -0.0798}]}, {"key": "ma", "label": "Most aces", "selections": [{"id": "ma|1", "label": "Sebastian Baez most aces", "model": 0.1098, "fair": 9.11, "books": {"dabble": 29.0}, "best": {"price": 29.0, "book": "dabble"}, "ev": 2.1842, "edge": 0.0753}, {"id": "ma|tie", "label": "Most aces — tie", "model": 0.0687, "fair": 14.56, "books": {"dabble": 21.0}, "best": {"price": 21.0, "book": "dabble"}, "ev": 0.4427, "edge": 0.0211}]}, {"key": "md", "label": "Most double faults", "selections": [{"id": "md|1", "label": "Sebastian Baez most double faults", "model": 0.336, "fair": 2.98, "books": {"dabble": 1.86}, "best": {"price": 1.86, "book": "dabble"}, "ev": -0.375, "edge": -0.2016}, {"id": "md|2", "label": "Yannick Hanfmann most double faults", "model": 0.4802, "fair": 2.08, "books": {"dabble": 2.0}, "best": {"price": 2.0, "book": "dabble"}, "ev": -0.0396, "edge": -0.0198}, {"id": "md|tie", "label": "Most double faults — tie", "model": 0.1838, "fair": 5.44, "books": {"dabble": 2.9}, "best": {"price": 2.9, "book": "dabble"}, "ev": -0.467, "edge": -0.161}]}]}, {"tour": "atp", "date": "20260723", "tournament": "Generali Open", "round": "Quarterfinal", "surface": "Hard", "player1": "Ignacio Buse", "player2": "Tomas Martin Etcheverry", "thin": false, "markets": [{"key": "mw", "label": "Match winner", "selections": [{"id": "mw|1", "label": "Ignacio Buse", "model": 0.4099, "fair": 2.44, "books": {"sportsbet": 1.8, "ladbrokes": 1.82, "tab": 1.85, "dabble": 1.82}, "best": {"price": 1.85, "book": "tab"}, "ev": -0.2417, "edge": -0.1306}, {"id": "mw|2", "label": "Tomas Martin Etcheverry", "model": 0.5901, "fair": 1.69, "books": {"sportsbet": 2.0, "ladbrokes": 1.94, "tab": 1.95, "dabble": 1.98}, "best": {"price": 2.0, "book": "sportsbet"}, "ev": 0.1802, "edge": 0.0901}]}, {"key": "sb", "label": "Set betting", "selections": [{"id": "sb|0-2", "label": "Tomas Martin Etcheverry 2-0", "model": 0.3963, "fair": 2.52, "books": {"sportsbet": 3.3, "ladbrokes": 3.0, "tab": 3.2, "dabble": 3.2}, "best": {"price": 3.3, "book": "sportsbet"}, "ev": 0.3078, "edge": 0.0933}, {"id": "sb|1-2", "label": "Tomas Martin Etcheverry 2-1", "model": 0.2936, "fair": 3.41, "books": {"sportsbet": 4.3, "ladbrokes": 4.2, "tab": 4.2, "dabble": 4.4}, "best": {"price": 4.4, "book": "dabble"}, "ev": 0.292, "edge": 0.0664}, {"id": "sb|2-0", "label": "Ignacio Buse 2-0", "model": 0.1373, "fair": 7.29, "books": {"sportsbet": 2.9, "ladbrokes": 2.7, "tab": 2.9, "dabble": 2.9}, "best": {"price": 2.9, "book": "sportsbet"}, "ev": -0.602, "edge": -0.2076}, {"id": "sb|2-1", "label": "Ignacio Buse 2-1", "model": 0.1728, "fair": 5.79, "books": {"sportsbet": 4.0, "ladbrokes": 4.0, "tab": 4.2, "dabble": 4.25}, "best": {"price": 4.25, "book": "dabble"}, "ev": -0.2656, "edge": -0.0625}]}, {"key": "tg", "label": "Total games", "selections": [{"id": "tg|O|22.5", "label": "Over 22.5", "model": 0.5858, "fair": 1.71, "books": {"tab": 1.8, "dabble": 1.82}, "best": {"price": 1.82, "book": "dabble"}, "ev": 0.0661, "edge": 0.0363}, {"id": "tg|U|22.5", "label": "Under 22.5", "model": 0.4142, "fair": 2.41, "books": {"tab": 1.95, "dabble": 1.95}, "best": {"price": 1.95, "book": "tab"}, "ev": -0.1923, "edge": -0.0986}]}, {"key": "gh", "label": "Games handicap", "selections": [{"id": "gh|1|-0.5", "label": "Ignacio Buse -0.5", "model": 0.2911, "fair": 3.43, "books": {"tab": 1.85, "dabble": 1.85}, "best": {"price": 1.85, "book": "tab"}, "ev": -0.4614, "edge": -0.2494}, {"id": "gh|2|0.5", "label": "Tomas Martin Etcheverry +0.5", "model": 0.7089, "fair": 1.41, "books": {"tab": 1.87, "dabble": 1.88}, "best": {"price": 1.88, "book": "dabble"}, "ev": 0.3326, "edge": 0.1769}]}, {"key": "sh", "label": "Set handicap", "selections": [{"id": "sh|1|-1.5", "label": "Ignacio Buse -1.5 sets", "model": 0.1373, "fair": 7.29, "books": {"dabble": 2.85}, "best": {"price": 2.85, "book": "dabble"}, "ev": -0.6088, "edge": -0.2136}, {"id": "sh|1|1.5", "label": "Ignacio Buse +1.5 sets", "model": 0.6037, "fair": 1.66, "books": {"sportsbet": 1.28, "dabble": 1.32}, "best": {"price": 1.32, "book": "dabble"}, "ev": -0.2031, "edge": -0.1539}, {"id": "sh|2|-1.5", "label": "Tomas Martin Etcheverry -1.5 sets", "model": 0.3963, "fair": 2.52, "books": {"sportsbet": 3.2, "dabble": 3.1}, "best": {"price": 3.2, "book": "sportsbet"}, "ev": 0.2682, "edge": 0.0838}, {"id": "sh|2|1.5", "label": "Tomas Martin Etcheverry +1.5 sets", "model": 0.8627, "fair": 1.16, "books": {"dabble": 1.37}, "best": {"price": 1.37, "book": "dabble"}, "ev": 0.182, "edge": 0.1328}]}, {"key": "pg", "label": "Player games", "selections": [{"id": "pg|1|O|12.5", "label": "Ignacio Buse games Over 12.5", "model": 0.5526, "fair": 1.81, "books": {"sportsbet": 1.77, "dabble": 1.8}, "best": {"price": 1.8, "book": "dabble"}, "ev": -0.0053, "edge": -0.003}, {"id": "pg|1|U|12.5", "label": "Ignacio Buse games Under 12.5", "model": 0.4474, "fair": 2.24, "books": {"sportsbet": 1.97, "dabble": 1.92}, "best": {"price": 1.97, "book": "sportsbet"}, "ev": -0.1186, "edge": -0.0602}, {"id": "pg|2|O|12.5", "label": "Tomas Martin Etcheverry games Over 12.5", "model": 0.6157, "fair": 1.62, "books": {"sportsbet": 1.84, "dabble": 1.88}, "best": {"price": 1.88, "book": "dabble"}, "ev": 0.1575, "edge": 0.0838}, {"id": "pg|2|U|12.5", "label": "Tomas Martin Etcheverry games Under 12.5", "model": 0.3843, "fair": 2.6, "books": {"sportsbet": 1.89, "dabble": 1.85}, "best": {"price": 1.89, "book": "sportsbet"}, "ev": -0.2737, "edge": -0.1448}]}, {"key": "ma", "label": "Most aces", "selections": [{"id": "ma|1", "label": "Ignacio Buse most aces", "model": 0.2851, "fair": 3.51, "books": {"dabble": 1.96}, "best": {"price": 1.96, "book": "dabble"}, "ev": -0.4412, "edge": -0.2251}, {"id": "ma|2", "label": "Tomas Martin Etcheverry most aces", "model": 0.6226, "fair": 1.61, "books": {"dabble": 1.78}, "best": {"price": 1.78, "book": "dabble"}, "ev": 0.1082, "edge": 0.0608}, {"id": "ma|tie", "label": "Most aces — tie", "model": 0.0922, "fair": 10.85, "books": {"dabble": 3.25}, "best": {"price": 3.25, "book": "dabble"}, "ev": -0.7004, "edge": -0.2155}]}, {"key": "md", "label": "Most double faults", "selections": [{"id": "md|1", "label": "Ignacio Buse most double faults", "model": 0.472, "fair": 2.12, "books": {"dabble": 1.73}, "best": {"price": 1.73, "book": "dabble"}, "ev": -0.1834, "edge": -0.106}, {"id": "md|2", "label": "Tomas Martin Etcheverry most double faults", "model": 0.3363, "fair": 2.97, "books": {"dabble": 2.25}, "best": {"price": 2.25, "book": "dabble"}, "ev": -0.2433, "edge": -0.1081}, {"id": "md|tie", "label": "Most double faults — tie", "model": 0.1917, "fair": 5.22, "books": {"dabble": 2.75}, "best": {"price": 2.75, "book": "dabble"}, "ev": -0.4728, "edge": -0.1719}]}]}, {"tour": "atp", "date": "20260723", "tournament": "Millennium Estoril Open", "round": "Round 2", "surface": "Hard", "player1": "Pablo Carreno Busta", "player2": "Luca Van Assche", "thin": false, "markets": [{"key": "mw", "label": "Match winner", "selections": [{"id": "mw|1", "label": "Pablo Carreno Busta", "model": 0.5527, "fair": 1.81, "books": {"sportsbet": 1.4, "ladbrokes": 1.44, "tab": 1.46, "dabble": 1.46}, "best": {"price": 1.46, "book": "tab"}, "ev": -0.1931, "edge": -0.1322}, {"id": "mw|2", "label": "Luca Van Assche", "model": 0.4473, "fair": 2.24, "books": {"sportsbet": 2.75, "ladbrokes": 2.7, "tab": 2.6, "dabble": 2.7}, "best": {"price": 2.75, "book": "sportsbet"}, "ev": 0.2301, "edge": 0.0837}]}, {"key": "sb", "label": "Set betting", "selections": [{"id": "sb|0-2", "label": "Luca Van Assche 2-0", "model": 0.5443, "fair": 1.84, "books": {"sportsbet": 4.9, "ladbrokes": 4.25, "tab": 5.0, "dabble": 5.0}, "best": {"price": 5.0, "book": "tab"}, "ev": 1.7215, "edge": 0.3443}, {"id": "sb|1-2", "label": "Luca Van Assche 2-1", "model": 0.2855, "fair": 3.5, "books": {"sportsbet": 5.5, "ladbrokes": 5.75, "tab": 5.0, "dabble": 5.0}, "best": {"price": 5.75, "book": "ladbrokes"}, "ev": 0.6414, "edge": 0.1116}, {"id": "sb|2-0", "label": "Pablo Carreno Busta 2-0", "model": 0.0688, "fair": 14.54, "books": {"sportsbet": 2.08, "ladbrokes": 1.96, "tab": 2.15, "dabble": 2.2}, "best": {"price": 2.2, "book": "dabble"}, "ev": -0.8487, "edge": -0.3858}, {"id": "sb|2-1", "label": "Pablo Carreno Busta 2-1", "model": 0.1015, "fair": 9.86, "books": {"sportsbet": 3.8, "ladbrokes": 3.8, "tab": 3.6, "dabble": 3.75}, "best": {"price": 3.8, "book": "sportsbet"}, "ev": -0.6144, "edge": -0.1617}]}, {"key": "tg", "label": "Total games", "selections": [{"id": "tg|O|22.5", "label": "Over 22.5", "model": 0.4996, "fair": 2.0, "books": {"tab": 1.92, "dabble": 1.92}, "best": {"price": 1.92, "book": "tab"}, "ev": -0.0409, "edge": -0.0213}, {"id": "tg|U|22.5", "label": "Under 22.5", "model": 0.5004, "fair": 2.0, "books": {"tab": 1.8, "dabble": 1.85}, "best": {"price": 1.85, "book": "dabble"}, "ev": -0.0742, "edge": -0.0401}]}, {"key": "gh", "label": "Games handicap", "selections": [{"id": "gh|1|-3.5", "label": "Pablo Carreno Busta -3.5", "model": 0.0643, "fair": 15.56, "books": {"tab": 2.0, "dabble": 2.0}, "best": {"price": 2.0, "book": "tab"}, "ev": -0.8715, "edge": -0.4357}, {"id": "gh|2|3.5", "label": "Luca Van Assche +3.5", "model": 0.9357, "fair": 1.07, "books": {"tab": 1.75, "dabble": 1.75}, "best": {"price": 1.75, "book": "tab"}, "ev": 0.6375, "edge": 0.3643}]}, {"key": "sh", "label": "Set handicap", "selections": [{"id": "sh|1|-1.5", "label": "Pablo Carreno Busta -1.5 sets", "model": 0.0688, "fair": 14.54, "books": {"dabble": 2.15}, "best": {"price": 2.15, "book": "dabble"}, "ev": -0.8522, "edge": -0.3964}, {"id": "sh|1|1.5", "label": "Pablo Carreno Busta +1.5 sets", "model": 0.4557, "fair": 2.19, "books": {"dabble": 1.15}, "best": {"price": 1.15, "book": "dabble"}, "ev": -0.476, "edge": -0.4139}, {"id": "sh|2|-1.5", "label": "Luca Van Assche -1.5 sets", "model": 0.5443, "fair": 1.84, "books": {"dabble": 4.75}, "best": {"price": 4.75, "book": "dabble"}, "ev": 1.5855, "edge": 0.3338}, {"id": "sh|2|1.5", "label": "Luca Van Assche +1.5 sets", "model": 0.9312, "fair": 1.07, "books": {"dabble": 1.62}, "best": {"price": 1.62, "book": "dabble"}, "ev": 0.5086, "edge": 0.314}]}, {"key": "pg", "label": "Player games", "selections": [{"id": "pg|1|O|12.5", "label": "Pablo Carreno Busta games Over 12.5", "model": 0.6241, "fair": 1.6, "books": {"dabble": 1.75}, "best": {"price": 1.75, "book": "dabble"}, "ev": 0.0922, "edge": 0.0527}, {"id": "pg|1|U|12.5", "label": "Pablo Carreno Busta games Under 12.5", "model": 0.3759, "fair": 2.66, "books": {"dabble": 2.0}, "best": {"price": 2.0, "book": "dabble"}, "ev": -0.2482, "edge": -0.1241}, {"id": "pg|2|O|11.5", "label": "Luca Van Assche games Over 11.5", "model": 0.6991, "fair": 1.43, "books": {"dabble": 1.75}, "best": {"price": 1.75, "book": "dabble"}, "ev": 0.2234, "edge": 0.1277}, {"id": "pg|2|U|11.5", "label": "Luca Van Assche games Under 11.5", "model": 0.3009, "fair": 3.32, "books": {"dabble": 2.0}, "best": {"price": 2.0, "book": "dabble"}, "ev": -0.3982, "edge": -0.1991}]}, {"key": "ma", "label": "Most aces", "selections": [{"id": "ma|1", "label": "Pablo Carreno Busta most aces", "model": 0.2888, "fair": 3.46, "books": {"dabble": 1.92}, "best": {"price": 1.92, "book": "dabble"}, "ev": -0.4455, "edge": -0.232}, {"id": "ma|2", "label": "Luca Van Assche most aces", "model": 0.6097, "fair": 1.64, "books": {"dabble": 1.8}, "best": {"price": 1.8, "book": "dabble"}, "ev": 0.0975, "edge": 0.0541}, {"id": "ma|tie", "label": "Most aces — tie", "model": 0.1015, "fair": 9.85, "books": {"dabble": 3.25}, "best": {"price": 3.25, "book": "dabble"}, "ev": -0.6701, "edge": -0.2062}]}]}, {"tour": "atp", "date": "20260724", "tournament": "Millennium Estoril Open", "round": "Quarterfinal", "surface": "Hard", "player1": "Hugo Gaston", "player2": "Juan Bautista Torres", "thin": true, "markets": [{"key": "mw", "label": "Match winner", "selections": [{"id": "mw|1", "label": "Hugo Gaston", "model": 0.3847, "fair": 2.6, "books": {"sportsbet": 1.25, "ladbrokes": 1.33, "dabble": 1.33}, "best": {"price": 1.33, "book": "ladbrokes"}, "ev": -0.4883, "edge": -0.3672}, {"id": "mw|2", "label": "Juan Bautista Torres", "model": 0.6153, "fair": 1.63, "books": {"sportsbet": 3.5, "ladbrokes": 3.2, "dabble": 3.3}, "best": {"price": 3.5, "book": "sportsbet"}, "ev": 1.1536, "edge": 0.3296}]}, {"key": "sb", "label": "Set betting", "selections": [{"id": "sb|0-2", "label": "Juan Bautista Torres 2-0", "model": 0.2416, "fair": 4.14, "books": {"ladbrokes": 5.25, "dabble": 6.0}, "best": {"price": 6.0, "book": "dabble"}, "ev": 0.4496, "edge": 0.0749}, {"id": "sb|1-2", "label": "Juan Bautista Torres 2-1", "model": 0.2457, "fair": 4.07, "books": {"ladbrokes": 6.6, "dabble": 6.0}, "best": {"price": 6.6, "book": "ladbrokes"}, "ev": 0.6216, "edge": 0.0942}, {"id": "sb|2-0", "label": "Hugo Gaston 2-0", "model": 0.2585, "fair": 3.87, "books": {"ladbrokes": 1.73, "dabble": 1.85}, "best": {"price": 1.85, "book": "dabble"}, "ev": -0.5217, "edge": -0.282}, {"id": "sb|2-1", "label": "Hugo Gaston 2-1", "model": 0.2542, "fair": 3.93, "books": {"ladbrokes": 3.9, "dabble": 4.0}, "best": {"price": 4.0, "book": "dabble"}, "ev": 0.0166, "edge": 0.0042}]}, {"key": "sh", "label": "Set handicap", "selections": [{"id": "sh|1|-1.5", "label": "Hugo Gaston -1.5 sets", "model": 0.2585, "fair": 3.87, "books": {"dabble": 1.82}, "best": {"price": 1.82, "book": "dabble"}, "ev": -0.5295, "edge": -0.2909}, {"id": "sh|1|1.5", "label": "Hugo Gaston +1.5 sets", "model": 0.7584, "fair": 1.32, "books": {"dabble": 1.11}, "best": {"price": 1.11, "book": "dabble"}, "ev": -0.1582, "edge": -0.1425}, {"id": "sh|2|-1.5", "label": "Juan Bautista Torres -1.5 sets", "model": 0.2416, "fair": 4.14, "books": {"dabble": 5.5}, "best": {"price": 5.5, "book": "dabble"}, "ev": 0.3288, "edge": 0.0598}, {"id": "sh|2|1.5", "label": "Juan Bautista Torres +1.5 sets", "model": 0.7415, "fair": 1.35, "books": {"dabble": 1.88}, "best": {"price": 1.88, "book": "dabble"}, "ev": 0.3939, "edge": 0.2095}]}]}]}